jinja2_matrix_filters/__init__.py
jinja2_matrix_filters/filters.py
jinja2_matrix_filters/matrix_filters/__init__.py
jinja2_matrix_filters/matrix_filters/bridge.py
jinja2_matrix_filters/matrix_filters/message_event_content.py
jinja2_matrix_filters/matrix_filters/user.py
jinja2_matrix_filters-0.1.0.dist-info/LICENSE
jinja2_matrix_filters-0.1.0.dist-info/METADATA
jinja2_matrix_filters-0.1.0.dist-info/WHEEL
jinja2_matrix_filters-0.1.0.dist-info/top_level.txt
jinja2_matrix_filters-0.1.0.dist-info/RECORD
