Metadata-Version: 2.1
Name: jinja2-matrix-filters
Version: 0.1.0
Summary: A Jinja plugin for handling Matrix data
Home-page: https://github.com/bramenn/jinja2-matrix-filters
Author: Alejandro Herrera
Author-email: bramendev@gmail.com
License: UNKNOWN
Platform: UNKNOWN
